{
  "id": "k3",
  "kidMode": true,
  "categories": [
    {
      "name": "Red Things",
      "difficulty": 0,
      "words": [
        {"text": "Apple", "backgroundColor": "#FA1616"},
        {"text": "Fire Truck", "backgroundColor": "#FA1616"},
        {"text": "Heart", "backgroundColor": "#FA1616"},
        {"text": "Strawberry", "backgroundColor": "#FA1616"},
        {"text": "Tomato", "backgroundColor": "#FA1616"},
        {"text": "Cherry", "backgroundColor": "#FA1616"},
        {"text": "Ladybug", "backgroundColor": "#FA1616"},
        {"text": "Rose", "backgroundColor": "#FA1616"},
        {"text": "Stop Sign", "backgroundColor": "#FA1616"}
      ]
    },
    {
      "name": "Yellow Things",
      "difficulty": 1,
      "words": [
        {"text": "Sun", "backgroundColor": "#ffd93d"},
        {"text": "Banana", "backgroundColor": "#ffd93d"},
        {"text": "Lemon", "backgroundColor": "#ffd93d"},
        {"text": "Star", "backgroundColor": "#ffd93d"},
        {"text": "School Bus", "backgroundColor": "#ffd93d"},
        {"text": "Cheese", "backgroundColor": "#ffd93d"},
        {"text": "Sunflower", "backgroundColor": "#ffd93d"},
        {"text": "Corn", "backgroundColor": "#ffd93d"}
      ]
    },
    {
      "name": "Blue Things",
      "difficulty": 2,
      "words": [
        {"text": "Sky", "backgroundColor": "#0881FC"},
        {"text": "Ocean", "backgroundColor": "#0881FC"},
        {"text": "Blueberry", "backgroundColor": "#0881FC"},
        {"text": "Whale", "backgroundColor": "#0881FC"},
        {"text": "Rain", "backgroundColor": "#0881FC"},
        {"text": "Jeans", "backgroundColor": "#0881FC"},
        {"text": "Dolphin", "backgroundColor": "#0881FC"},
        {"text": "Ice", "backgroundColor": "#0881FC"},
        {"text": "Bluebird", "backgroundColor": "#0881FC"}
      ]
    },
    {
      "name": "Green Things",
      "difficulty": 3,
      "words": [
        {"text": "Grass", "backgroundColor": "#0DD225"},
        {"text": "Frog", "backgroundColor": "#0DD225"},
        {"text": "Leaf", "backgroundColor": "#0DD225"},
        {"text": "Tree", "backgroundColor": "#0DD225"},
        {"text": "Broccoli", "backgroundColor": "#0DD225"},
        {"text": "Turtle", "backgroundColor": "#0DD225"},
        {"text": "Peas", "backgroundColor": "#0DD225"},
        {"text": "Alligator", "backgroundColor": "#0DD225"},
        {"text": "Pickle", "backgroundColor": "#0DD225"}
      ]
    }
  ]
}
